easierselenium/BaseWebInteractor.py
easierselenium/GoogleCloudInteractor.py
easierselenium/__init__.py
easierselenium/containers/chrome90/Dockerfile
easierselenium/containers/chrome90/requirements.txt
easierselenium/examples/FiveThirtyEight.py
easierselenium/examples/__init__.py
easierselenium-0.3.1.dist-info/LICENSE.txt
easierselenium-0.3.1.dist-info/METADATA
easierselenium-0.3.1.dist-info/WHEEL
easierselenium-0.3.1.dist-info/RECORD
