Metadata-Version: 2.1
Name: easierselenium
Version: 0.3.1
Summary: Tools to make working with selenium for web scraping easier
Author: Eugene Brown
Author-email: efbbrown@gmail.com
Requires-Python: >=3.8,<4.0
Classifier: Programming Language :: Python :: 3
Classifier: Programming Language :: Python :: 3.8
Classifier: Programming Language :: Python :: 3.9
Classifier: Programming Language :: Python :: 3.10
Classifier: Programming Language :: Python :: 3.11
Requires-Dist: PyYAML (>=6.0,<7.0)
Requires-Dist: pandas (>=1.5.3,<2.0.0)
Requires-Dist: selenium (>=4.7.2,<5.0.0)
Requires-Dist: webdriver-manager (>=3.8.5,<4.0.0)
